{
    "version": "2.6.14",
    "architecture": {
        "64bit": {
            "url": "http://download.haijin-boys.com/download/Mery-x64-2.6.14.zip",
            "hash": "8ed74d9946ee8e6ea49895700c58498359f4dd7bfa68cf4340b30b234011ca88"
        },
        "32bit": {
            "url": "http://download.haijin-boys.com/download/Mery-2.6.14.zip",
            "hash": "6b7dd2678d12e29bd6573284c27107c1f8dbb05735b5b8c1ca84d7c0ad801304"
        }
    },
    "homepage": "https://www.haijin-boys.com/wiki/",
    "extract_dir": "Mery",
    "bin": "Mery.exe",
    "pre_install": [
        "if((Test-Path(\"$env:TEMP\\__scoop__preserved\"))) { Write-Output \"[pre_install] Removing temporary preserved folder\"; Remove-Item \"$env:TEMP\\__scoop__preserved\" -Recurse -Force }",
        "Write-Output \"[pre_install] Creating temporary preserved folder\"; New-Item \"$env:TEMP\\__scoop__preserved\" -type directory | Out-Null",
        "Write-Output \"[pre_install] Preserving original files\"; Copy-Item \"$dir\\*\" \"$env:TEMP\\__scoop__preserved\" -Recurse -Force"
    ],
    "persist": "Plugins",
    "post_install": [
        "Write-Output \"[post_install] Overwriting from original files\"; Copy-Item \"$env:TEMP\\__scoop__preserved\\*\" \"$dir\" -Recurse -Force",
        "Write-Output \"[post_install] Removing temporary preserved folder\"; Remove-Item \"$env:TEMP\\__scoop__preserved\" -Recurse -Force"
    ],
    "shortcuts": [
        [
            "Mery.exe",
            "Mery (ベータ版)"
        ]
    ],
    "checkver": {
        "url": "https://www.haijin-boys.com/software/mery",
        "re": "Ver ([\\d.]+)"
    },
    "autoupdate": {
        "architecture": {
            "64bit": {
                "url": "http://download.haijin-boys.com/download/Mery-x64-$version.zip"
            },
            "32bit": {
                "url": "http://download.haijin-boys.com/download/Mery-$version.zip"
            }
        }
    }
}
