{
    "version": "52.0.2871.64",
    "url": "https://download3.operacdn.com/pub/opera/desktop/52.0.2871.64/win/Opera_52.0.2871.64_Setup.exe#dl.7z",
    "homepage": "https://www.opera.com/",
    "bin": "Opera.exe",
    "hash": "0dfb50207543b867f99972aae31a8b5af749ab9280eaa889f739b4f41d87cb06",
    "shortcuts": [
        [
            "Opera.exe",
            "Opera"
        ]
    ],
    "checkver": {
        "url": "https://download3.operacdn.com/pub/opera/desktop/",
        "re": "([\\d]+[.][\\d]+[.][\\d]+[.][\\d]+)",
        "reverse": true
    },
    "autoupdate": {
        "url": "https://download3.operacdn.com/pub/opera/desktop/$version/win/Opera_$version_Setup.exe#dl.7z"
    }
}
